Assignment-2/fsm_gray.v
`timescale 1ns/1ps
//============================================================
// VDF Assignment-2, Q2(a)
// Mealy FSM, 5 states, 2-bit input, 2-bit output
// State encoding : GRAY  (3 bits)
//   S1 = 000, S2 = 001, S3 = 011, S4 = 010, S5 = 110
//   consecutive codes differ in exactly one bit
//============================================================

module fsm_gray (
    input  wire       clk,
    input  wire       rst,   // synchronous, active high -> S1
    input  wire [1:0] in,
    output reg  [1:0] out
);

    // ---------------- gray state codes ----------------
    localparam [2:0] S1 = 3'b000,
                     S2 = 3'b001,
                     S3 = 3'b011,
                     S4 = 3'b010,
                     S5 = 3'b110;

    (* fsm_encoding = "none" *) reg [2:0] cur_state;
    reg [2:0] next_state;

    // ---------------- state register ----------------
    always @(posedge clk) begin
        if (rst)
            cur_state <= S1;
        else
            cur_state <= next_state;
    end

    // ---------------- next state + output logic ----------------
    // Mealy: output is a function of (cur_state, in)
    always @(*) begin
        // safe defaults (avoid latches / unknown propagation)
        next_state = S1;
        out        = 2'b00;

        case (cur_state)

            S1: case (in)
                    2'b00: begin next_state = S1; out = 2'b01; end
                    2'b01: begin next_state = S1; out = 2'b00; end
                    2'b10: begin next_state = S2; out = 2'b01; end
                    2'b11: begin next_state = S3; out = 2'b00; end
                endcase

            S2: case (in)
                    2'b00: begin next_state = S1; out = 2'b11; end
                    2'b01: begin next_state = S3; out = 2'b11; end
                    2'b10: begin next_state = S2; out = 2'b10; end
                    2'b11: begin next_state = S4; out = 2'b10; end
                endcase

            S3: case (in)
                    2'b00: begin next_state = S1; out = 2'b00; end
                    2'b01: begin next_state = S5; out = 2'b01; end
                    2'b10: begin next_state = S3; out = 2'b10; end
                    2'b11: begin next_state = S4; out = 2'b00; end
                endcase

            S4: case (in)
                    2'b00: begin next_state = S3; out = 2'b11; end
                    2'b01: begin next_state = S5; out = 2'b01; end
                    2'b10: begin next_state = S5; out = 2'b01; end
                    2'b11: begin next_state = S4; out = 2'b11; end
                endcase

            S5: case (in)
                    2'b00: begin next_state = S5; out = 2'b00; end
                    2'b01: begin next_state = S1; out = 2'b00; end
                    2'b10: begin next_state = S3; out = 2'b00; end
                    2'b11: begin next_state = S5; out = 2'b11; end
                endcase

            // unused gray codes 100, 101, 111 -> recover to S1
            default: begin next_state = S1; out = 2'b00; end

        endcase
    end

endmodule

Assignment-2/tb_fsm.v
//============================================================
// VDF Assignment-2, Q2(b)
// Self-checking testbench for the 5-state Mealy FSM.
//
// The stimulus is a directed walk that exercises ALL 20 arcs
// of the state diagram (5 states x 4 input combinations), plus
// the reset behaviour. A golden reference model (written from
// the state diagram, independent of the DUT's encoding) predicts
// the output every cycle and any mismatch is reported.
//
// Compile (gray version)   : iverilog -Wall -o test fsm_gray.v tb_fsm.v
// Compile (one-hot version): iverilog -Wall -DONEHOT -o test fsm_onehot.v tb_fsm.v
// Run                      : vvp test
// View                     : gtkwave fsm.vcd
//============================================================

`timescale 1ns/1ps

module tb_fsm;

    reg        clk = 1'b0;
    reg        rst;
    reg  [1:0] in;
    wire [1:0] out;

    integer errors = 0;
    integer i;

    // ---------------- DUT ----------------
`ifdef ONEHOT
    fsm_onehot dut (.clk(clk), .rst(rst), .in(in), .out(out));
`else
    fsm_gray   dut (.clk(clk), .rst(rst), .in(in), .out(out));
`endif

    // ---------------- clock : 10 ns period ----------------
    always #5 clk = ~clk;

    // ---------------- golden reference model ----------------
    // states numbered 1..5, encoding-independent
    integer ref_state;

    // returns {next_state[2:0], expected_out[1:0]}
    function [4:0] model;
        input integer s;
        input [1:0]   stim;
        begin
            model = 5'b0;
            case (s)
            1: case (stim)
                 2'b00: model = {3'd1, 2'b01};
                 2'b01: model = {3'd1, 2'b00};
                 2'b10: model = {3'd2, 2'b01};
                 2'b11: model = {3'd3, 2'b00};
               endcase
            2: case (stim)
                 2'b00: model = {3'd1, 2'b11};
                 2'b01: model = {3'd3, 2'b11};
                 2'b10: model = {3'd2, 2'b10};
                 2'b11: model = {3'd4, 2'b10};
               endcase
            3: case (stim)
                 2'b00: model = {3'd1, 2'b00};
                 2'b01: model = {3'd5, 2'b01};
                 2'b10: model = {3'd3, 2'b10};
                 2'b11: model = {3'd4, 2'b00};
               endcase
            4: case (stim)
                 2'b00: model = {3'd3, 2'b11};
                 2'b01: model = {3'd5, 2'b01};
                 2'b10: model = {3'd5, 2'b01};
                 2'b11: model = {3'd4, 2'b11};
               endcase
            5: case (stim)
                 2'b00: model = {3'd5, 2'b00};
                 2'b01: model = {3'd1, 2'b00};
                 2'b10: model = {3'd3, 2'b00};
                 2'b11: model = {3'd5, 2'b11};
               endcase
            endcase
        end
    endfunction

    // ---------------- one stimulus vector ----------------
    task apply;
        input [1:0] stim;
        reg   [4:0] pred;
        begin
            @(negedge clk);
            in   = stim;
            pred = model(ref_state, stim);
            #1;                             // let combinational output settle
            if (out !== pred[1:0]) begin
                errors = errors + 1;
                $display("[%0t] MISMATCH: S%0d in=%b -> out=%b (expected %b)",
                         $time, ref_state, stim, out, pred[1:0]);
            end else begin
                $display("[%0t] S%0d  in=%b  out=%b  -> S%0d",
                         $time, ref_state, stim, out, pred[4:2]);
            end
            @(posedge clk);
            #1;
            ref_state = pred[4:2];          // reference follows the DUT
        end
    endtask

    // ---------------- directed walk covering all 20 arcs ----------------
    // S1:00 S1:01 S1:10 S2:10 S2:00 (S1:10) S2:01 S3:10 S3:00 S1:11
    // S3:11 S4:11 S4:00 S3:01 S5:00 S5:11 S5:10 (S3:11) S4:10 S5:01
    // (S1:10) S2:11 S4:01 S5:01
    reg [1:0] walk [0:23];
    initial begin
        walk[0]=2'b00; walk[1]=2'b01; walk[2]=2'b10; walk[3]=2'b10;
        walk[4]=2'b00; walk[5]=2'b10; walk[6]=2'b01; walk[7]=2'b10;
        walk[8]=2'b00; walk[9]=2'b11; walk[10]=2'b11; walk[11]=2'b11;
        walk[12]=2'b00; walk[13]=2'b01; walk[14]=2'b00; walk[15]=2'b11;
        walk[16]=2'b10; walk[17]=2'b11; walk[18]=2'b10; walk[19]=2'b01;
        walk[20]=2'b10; walk[21]=2'b11; walk[22]=2'b01; walk[23]=2'b01;
    end

    // ---------------- main stimulus ----------------
    initial begin
        $dumpfile("fsm.vcd");
        $dumpvars(0, tb_fsm);

        // reset
        rst = 1'b1;
        in  = 2'b00;
        ref_state = 1;
        @(posedge clk);
        @(posedge clk);
        #1 rst = 1'b0;
        $display("--- reset released, FSM should be in S1 ---");

        // walk through every arc
        for (i = 0; i < 24; i = i + 1)
            apply(walk[i]);

        // check reset from a non-initial state
        @(negedge clk); in = 2'b11; @(posedge clk);   // move away from S1
        @(negedge clk); rst = 1'b1;
        @(posedge clk); #1 rst = 1'b0;
        ref_state = 1;
        $display("--- synchronous reset re-applied, FSM back in S1 ---");
        apply(2'b10);   // must behave like S1 again

        if (errors == 0)
            $display("\nTEST PASSED : all %0d checks matched the reference model", 25);
        else
            $display("\nTEST FAILED : %0d mismatches", errors);

        #20 $finish;
    end

endmodule

Assignment-2/fsm.vcd
$date
	Thu Sep 10 12:52:58 2026
$end
$version
	Icarus Verilog
$end
$timescale
	1ps
$end
$scope module tb_fsm $end
$var wire 2 ! out [1:0] $end
$var reg 1 " clk $end
$var reg 2 # in [1:0] $end
$var reg 1 $ rst $end
$var integer 32 % errors [31:0] $end
$var integer 32 & i [31:0] $end
$var integer 32 ' ref_state [31:0] $end
$scope function model $end
$var reg 2 ( stim [1:0] $end
$var integer 32 ) s [31:0] $end
$upscope $end
$scope module dut $end
$var wire 1 " clk $end
$var wire 2 * in [1:0] $end
$var wire 1 $ rst $end
$var reg 3 + cur_state [2:0] $end
$var reg 3 , next_state [2:0] $end
$var reg 2 - out [1:0] $end
$upscope $end
$scope task apply $end
$var reg 5 . pred [4:0] $end
$var reg 2 / stim [1:0] $end
$upscope $end
$upscope $end
$enddefinitions $end
#0
$dumpvars
bx /
bx .
b0 -
b0 ,
bx +
b0 *
bx )
bx (
b1 '
bx &
b0 %
1$
b0 #
0"
b0 !
$end
#5000
b1 !
b1 -
b0 +
1"
#10000
0"
#15000
1"
#16000
b0 /
b0 &
0$
#20000
b101 .
b1 )
b0 (
0"
#25000
1"
#26000
b1 /
b1 &
#30000
b0 !
b0 -
b100 .
b1 (
b1 #
b1 *
0"
#35000
1"
#36000
b10 /
b10 &
#40000
b1 !
b1 -
b1 ,
b1001 .
b10 (
b10 #
b10 *
0"
#45000
b10 !
b10 -
b1 ,
b1 +
1"
#46000
b11 &
b10 '
#50000
b1010 .
b10 )
0"
#55000
1"
#56000
b0 /
b100 &
#60000
b11 !
b11 -
b0 ,
b111 .
b0 (
b0 #
b0 *
0"
#65000
b1 !
b1 -
b0 +
1"
#66000
b10 /
b101 &
b1 '
#70000
b1 ,
b1 !
b1 -
b1001 .
b1 )
b10 (
b10 #
b10 *
0"
#75000
b10 !
b10 -
b1 ,
b1 +
1"
#76000
b1 /
b110 &
b10 '
#80000
b11 !
b11 -
b11 ,
b1111 .
b10 )
b1 (
b1 #
b1 *
0"
#85000
b1 !
b1 -
b110 ,
b11 +
1"
#86000
b10 /
b111 &
b11 '
#90000
b10 !
b10 -
b11 ,
b1110 .
b11 )
b10 (
b10 #
b10 *
0"
#95000
1"
#96000
b0 /
b1000 &
#100000
b0 !
b0 -
b0 ,
b100 .
b0 (
b0 #
b0 *
0"
#105000
b1 !
b1 -
b0 +
1"
#106000
b11 /
b1001 &
b1 '
#110000
b11 ,
b0 !
b0 -
b1100 .
b1 )
b11 (
b11 #
b11 *
0"
#115000
b10 ,
b11 +
1"
#116000
b1010 &
b11 '
#120000
b10000 .
b11 )
0"
#125000
b11 !
b11 -
b10 ,
b10 +
1"
#126000
b1011 &
b100 '
#130000
b10011 .
b100 )
0"
#135000
1"
#136000
b0 /
b1100 &
#140000
b11 !
b11 -
b11 ,
b1111 .
b0 (
b0 #
b0 *
0"
#145000
b0 !
b0 -
b0 ,
b11 +
1"
#146000
b1 /
b1101 &
b11 '
#150000
b1 !
b1 -
b110 ,
b10101 .
b11 )
b1 (
b1 #
b1 *
0"
#155000
b0 !
b0 -
b0 ,
b110 +
1"
#156000
b0 /
b1110 &
b101 '
#160000
b110 ,
b10100 .
b101 )
b0 (
b0 #
b0 *
0"
#165000
1"
#166000
b11 /
b1111 &
#170000
b11 !
b11 -
b110 ,
b10111 .
b11 (
b11 #
b11 *
0"
#175000
1"
#176000
b10 /
b10000 &
#180000
b0 !
b0 -
b11 ,
b1100 .
b10 (
b10 #
b10 *
0"
#185000
b10 !
b10 -
b11 ,
b11 +
1"
#186000
b11 /
b10001 &
b11 '
#190000
b0 !
b0 -
b10 ,
b10000 .
b11 )
b11 (
b11 #
b11 *
0"
#195000
b11 !
b11 -
b10 ,
b10 +
1"
#196000
b10 /
b10010 &
b100 '
#200000
b1 !
b1 -
b110 ,
b10101 .
b100 )
b10 (
b10 #
b10 *
0"
#205000
b0 !
b0 -
b11 ,
b110 +
1"
#206000
b1 /
b10011 &
b101 '
#210000
b0 ,
b100 .
b101 )
b1 (
b1 #
b1 *
0"
#215000
b0 +
1"
#216000
b10 /
b10100 &
b1 '
#220000
b1 !
b1 -
b1 ,
b1001 .
b1 )
b10 (
b10 #
b10 *
0"
#225000
b10 !
b10 -
b1 ,
b1 +
1"
#226000
b11 /
b10101 &
b10 '
#230000
b10 !
b10 -
b10 ,
b10010 .
b10 )
b11 (
b11 #
b11 *
0"
#235000
b11 !
b11 -
b10 ,
b10 +
1"
#236000
b1 /
b10110 &
b100 '
#240000
b1 !
b1 -
b110 ,
b10101 .
b100 )
b1 (
b1 #
b1 *
0"
#245000
b0 !
b0 -
b0 ,
b110 +
1"
#246000
b10111 &
b101 '
#250000
b100 .
b101 )
0"
#255000
b0 +
1"
#256000
b11000 &
b1 '
#260000
b11 ,
b11 #
b11 *
0"
#265000
b10 ,
b11 +
1"
#270000
1$
0"
#275000
b11 ,
b0 +
1"
#276000
b10 /
0$
#280000
b1 !
b1 -
b1 ,
b1001 .
b1 )
b10 (
b10 #
b10 *
0"
#285000
b10 !
b10 -
b1 ,
b1 +
1"
#286000
b10 '
