Assignment-2/fsm_gray.v
`timescale 1ns/1ps
//============================================================
// VDF Assignment-2, Q2(a)
// Mealy FSM, 5 states, 2-bit input, 2-bit output
// State encoding : GRAY  (3 bits)
//   S1 = 000, S2 = 001, S3 = 011, S4 = 010, S5 = 110
//   consecutive codes differ in exactly one bit
//============================================================

module fsm_gray (
    input  wire       clk,
    input  wire       rst,   // synchronous, active high -> S1
    input  wire [1:0] in,
    output reg  [1:0] out
);

    // ---------------- gray state codes ----------------
    localparam [2:0] S1 = 3'b000,
                     S2 = 3'b001,
                     S3 = 3'b011,
                     S4 = 3'b010,
                     S5 = 3'b110;

    (* fsm_encoding = "none" *) reg [2:0] cur_state;
    reg [2:0] next_state;

    // ---------------- state register ----------------
    always @(posedge clk) begin
        if (rst)
            cur_state <= S1;
        else
            cur_state <= next_state;
    end

    // ---------------- next state + output logic ----------------
    // Mealy: output is a function of (cur_state, in)
    always @(*) begin
        // safe defaults (avoid latches / unknown propagation)
        next_state = S1;
        out        = 2'b00;

        case (cur_state)

            S1: case (in)
                    2'b00: begin next_state = S1; out = 2'b01; end
                    2'b01: begin next_state = S1; out = 2'b00; end
                    2'b10: begin next_state = S2; out = 2'b01; end
                    2'b11: begin next_state = S3; out = 2'b00; end
                endcase

            S2: case (in)
                    2'b00: begin next_state = S1; out = 2'b11; end
                    2'b01: begin next_state = S3; out = 2'b11; end
                    2'b10: begin next_state = S2; out = 2'b10; end
                    2'b11: begin next_state = S4; out = 2'b10; end
                endcase

            S3: case (in)
                    2'b00: begin next_state = S1; out = 2'b00; end
                    2'b01: begin next_state = S5; out = 2'b01; end
                    2'b10: begin next_state = S3; out = 2'b10; end
                    2'b11: begin next_state = S4; out = 2'b00; end
                endcase

            S4: case (in)
                    2'b00: begin next_state = S3; out = 2'b11; end
                    2'b01: begin next_state = S5; out = 2'b01; end
                    2'b10: begin next_state = S5; out = 2'b01; end
                    2'b11: begin next_state = S4; out = 2'b11; end
                endcase

            S5: case (in)
                    2'b00: begin next_state = S5; out = 2'b00; end
                    2'b01: begin next_state = S1; out = 2'b00; end
                    2'b10: begin next_state = S3; out = 2'b00; end
                    2'b11: begin next_state = S5; out = 2'b11; end
                endcase

            // unused gray codes 100, 101, 111 -> recover to S1
            default: begin next_state = S1; out = 2'b00; end

        endcase
    end

endmodule

Assignment-2/tb_cov.v
//============================================================
// VDF Assignment-2, Q2(d)
// Stimulus-only testbench used for COVERED line-coverage scoring.
//
// It applies exactly the same 24-vector directed walk as tb_fsm.v
// (all 20 arcs of the state diagram), plus the reset sequence, but
// contains no functions and no tasks, because the Covered 2009
// parser cannot handle the self-checking reference model used in
// tb_fsm.v. Since line coverage is measured on fsm_gray.v and the
// stimulus is identical, the coverage figures are unaffected.
//
//   iverilog -Wall -o test_cov fsm_gray.v tb_cov.v
//   vvp test_cov
//   covered score -t tb_cov -v tb_cov.v -v fsm_gray.v -vcd fsm_cov.vcd -o fsm.cdd
//   covered report -d v fsm.cdd
//============================================================

`timescale 1ns/1ps

module tb_cov;

    reg        clk = 1'b0;
    reg        rst;
    reg  [1:0] in;
    wire [1:0] out;

    fsm_gray dut (.clk(clk), .rst(rst), .in(in), .out(out));

    always #5 clk = ~clk;

    initial begin
        $dumpfile("fsm_cov.vcd");
        $dumpvars(0, tb_cov);

        // ---- reset into S1 ----
        rst = 1'b1;
        in  = 2'b00;
        @(posedge clk);
        @(posedge clk);
        #1 rst = 1'b0;

        // ---- directed walk covering all 20 arcs ----
        @(negedge clk); in = 2'b00;   // S1 / 00 -> S1
        @(negedge clk); in = 2'b01;   // S1 / 01 -> S1
        @(negedge clk); in = 2'b10;   // S1 / 10 -> S2
        @(negedge clk); in = 2'b10;   // S2 / 10 -> S2
        @(negedge clk); in = 2'b00;   // S2 / 00 -> S1
        @(negedge clk); in = 2'b10;   // S1 / 10 -> S2
        @(negedge clk); in = 2'b01;   // S2 / 01 -> S3
        @(negedge clk); in = 2'b10;   // S3 / 10 -> S3
        @(negedge clk); in = 2'b00;   // S3 / 00 -> S1
        @(negedge clk); in = 2'b11;   // S1 / 11 -> S3
        @(negedge clk); in = 2'b11;   // S3 / 11 -> S4
        @(negedge clk); in = 2'b11;   // S4 / 11 -> S4
        @(negedge clk); in = 2'b00;   // S4 / 00 -> S3
        @(negedge clk); in = 2'b01;   // S3 / 01 -> S5
        @(negedge clk); in = 2'b00;   // S5 / 00 -> S5
        @(negedge clk); in = 2'b11;   // S5 / 11 -> S5
        @(negedge clk); in = 2'b10;   // S5 / 10 -> S3
        @(negedge clk); in = 2'b11;   // S3 / 11 -> S4
        @(negedge clk); in = 2'b10;   // S4 / 10 -> S5
        @(negedge clk); in = 2'b01;   // S5 / 01 -> S1
        @(negedge clk); in = 2'b10;   // S1 / 10 -> S2
        @(negedge clk); in = 2'b11;   // S2 / 11 -> S4
        @(negedge clk); in = 2'b01;   // S4 / 01 -> S5
        @(negedge clk); in = 2'b01;   // S5 / 01 -> S1

        // ---- reset applied from a non-initial state ----
        @(negedge clk); in = 2'b11;
        @(negedge clk); rst = 1'b1;
        @(posedge clk); #1 rst = 1'b0;
        @(negedge clk); in = 2'b10;

        @(negedge clk);
        #20 $display("Coverage stimulus complete.");
        $finish;
    end

endmodule

Assignment-2/fsm_cov.vcd
$date
	Thu Sep 10 12:55:14 2026
$end
$version
	Icarus Verilog
$end
$timescale
	1ps
$end
$scope module tb_cov $end
$var wire 2 ! out [1:0] $end
$var reg 1 " clk $end
$var reg 2 # in [1:0] $end
$var reg 1 $ rst $end
$scope module dut $end
$var wire 1 " clk $end
$var wire 2 % in [1:0] $end
$var wire 1 $ rst $end
$var reg 3 & cur_state [2:0] $end
$var reg 3 ' next_state [2:0] $end
$var reg 2 ( out [1:0] $end
$upscope $end
$upscope $end
$enddefinitions $end
#0
$dumpvars
b0 (
b0 '
bx &
b0 %
1$
b0 #
0"
b0 !
$end
#5000
b1 !
b1 (
b0 &
1"
#10000
0"
#15000
1"
#16000
0$
#20000
0"
#25000
1"
#30000
b0 !
b0 (
b1 #
b1 %
0"
#35000
1"
#40000
b1 !
b1 (
b1 '
b10 #
b10 %
0"
#45000
b10 !
b10 (
b1 '
b1 &
1"
#50000
0"
#55000
1"
#60000
b11 !
b11 (
b0 '
b0 #
b0 %
0"
#65000
b1 !
b1 (
b0 &
1"
#70000
b1 '
b1 !
b1 (
b10 #
b10 %
0"
#75000
b10 !
b10 (
b1 '
b1 &
1"
#80000
b11 !
b11 (
b11 '
b1 #
b1 %
0"
#85000
b1 !
b1 (
b110 '
b11 &
1"
#90000
b10 !
b10 (
b11 '
b10 #
b10 %
0"
#95000
1"
#100000
b0 !
b0 (
b0 '
b0 #
b0 %
0"
#105000
b1 !
b1 (
b0 &
1"
#110000
b11 '
b0 !
b0 (
b11 #
b11 %
0"
#115000
b10 '
b11 &
1"
#120000
0"
#125000
b11 !
b11 (
b10 '
b10 &
1"
#130000
0"
#135000
1"
#140000
b11 !
b11 (
b11 '
b0 #
b0 %
0"
#145000
b0 !
b0 (
b0 '
b11 &
1"
#150000
b1 !
b1 (
b110 '
b1 #
b1 %
0"
#155000
b0 !
b0 (
b0 '
b110 &
1"
#160000
b110 '
b0 #
b0 %
0"
#165000
1"
#170000
b11 !
b11 (
b110 '
b11 #
b11 %
0"
#175000
1"
#180000
b0 !
b0 (
b11 '
b10 #
b10 %
0"
#185000
b10 !
b10 (
b11 '
b11 &
1"
#190000
b0 !
b0 (
b10 '
b11 #
b11 %
0"
#195000
b11 !
b11 (
b10 '
b10 &
1"
#200000
b1 !
b1 (
b110 '
b10 #
b10 %
0"
#205000
b0 !
b0 (
b11 '
b110 &
1"
#210000
b0 '
b1 #
b1 %
0"
#215000
b0 &
1"
#220000
b1 !
b1 (
b1 '
b10 #
b10 %
0"
#225000
b10 !
b10 (
b1 '
b1 &
1"
#230000
b10 !
b10 (
b10 '
b11 #
b11 %
0"
#235000
b11 !
b11 (
b10 '
b10 &
1"
#240000
b1 !
b1 (
b110 '
b1 #
b1 %
0"
#245000
b0 !
b0 (
b0 '
b110 &
1"
#250000
0"
#255000
b0 &
1"
#260000
b11 '
b11 #
b11 %
0"
#265000
b10 '
b11 &
1"
#270000
1$
0"
#275000
b11 '
b0 &
1"
#276000
0$
#280000
b1 !
b1 (
b1 '
b10 #
b10 %
0"
#285000
b10 !
b10 (
b1 '
b1 &
1"
